manim_ds/__init__.py
manim_ds/animations.py
manim_ds/colours.py
manim_ds/mlist.py
manim_ds-0.0.1a1.dist-info/METADATA
manim_ds-0.0.1a1.dist-info/WHEEL
manim_ds-0.0.1a1.dist-info/top_level.txt
manim_ds-0.0.1a1.dist-info/RECORD
