Metadata-Version: 2.1
Name: manim-ds
Version: 0.0.1a1
Summary: Manim utilities for creating data structure animations
Home-page: https://github.com/James-Ansley/manim-ds
Author: James Finnie-Ansley
License: MIT License
Requires-Python: >=3.10
Requires-Dist: manim (~=0.16.0.post0)
